caworker/__init__.py
caworker/worker.py
caworker-0.1.4.dist-info/LICENSE
caworker-0.1.4.dist-info/METADATA
caworker-0.1.4.dist-info/WHEEL
caworker-0.1.4.dist-info/top_level.txt
caworker-0.1.4.dist-info/RECORD
