Metadata-Version: 2.1
Name: caworker
Version: 0.1.4
Summary: Camunda Worker
Home-page: https://github.com/gpcortes/caworker.git
Author: Gustavo Côrtes
Author-email: gpcortes@gmail.com
License: BSD 2-clause
Classifier: Development Status :: 1 - Planning
Classifier: Intended Audience :: Science/Research
Classifier: License :: OSI Approved :: BSD License
Classifier: Operating System :: POSIX :: Linux
Classifier: Programming Language :: Python :: 3.7
License-File: LICENSE
Requires-Dist: requests (>=2.27.1)
Requires-Dist: pycamunda (>=0.6.1)
Requires-Dist: python-dotenv (>=0.19.2)
